pylogops/__init__.py
pylogops/logger.py
pylogops-1.2.0.dist-info/LICENSE
pylogops-1.2.0.dist-info/METADATA
pylogops-1.2.0.dist-info/WHEEL
pylogops-1.2.0.dist-info/top_level.txt
pylogops-1.2.0.dist-info/RECORD
