Metadata-Version: 2.1
Name: pylogops
Version: 1.2.0
Summary: A simple json formatter for python logging.
Home-page: http://github.com/telefonicaid/pylogops
Author: Eduardo Alonso
Author-email: eduardo.alonsogarcia@telefonica.com
Maintainer: Eduardo Alonso
Maintainer-email: eduardo.alonsogarcia@telefonica.com
License: BSD
Platform: OS Independent
Classifier: Intended Audience :: Developers
Classifier: License :: OSI Approved :: BSD License
Classifier: Operating System :: OS Independent
Classifier: Programming Language :: Python
Classifier: Programming Language :: Python :: 2
Classifier: Programming Language :: Python :: 2.7
Classifier: Programming Language :: Python :: 3
Classifier: Programming Language :: Python :: 3.4
Classifier: Programming Language :: Python :: 3.5
Classifier: Programming Language :: Python :: 3.6
Classifier: Programming Language :: Python :: 3.7
Classifier: Programming Language :: Python :: Implementation :: CPython
Classifier: Programming Language :: Python :: Implementation :: PyPy
Requires-Dist: six
